masht/__about__.py
masht/__init__.py
masht/md_to_html.py
masht-0.1.dev11.dist-info/LICENSE
masht-0.1.dev11.dist-info/METADATA
masht-0.1.dev11.dist-info/WHEEL
masht-0.1.dev11.dist-info/entry_points.txt
masht-0.1.dev11.dist-info/top_level.txt
masht-0.1.dev11.dist-info/RECORD
