Metadata-Version: 2.1
Name: masht
Version: 0.1.dev11
Summary: Markdown AS HTml: Creates a HTML version of a Markdown file.
Author-email: Bill Melvin <bill@sbillmelvin.com>
License: MIT
Project-URL: Documentation, https://github.com/wmelvin/masht#readme
Project-URL: Issues, https://github.com/wmelvin/masht/issues
Project-URL: Source, https://github.com/wmelvin/masht
Keywords: markdown,html,converter
Requires-Python: >=3.9
License-File: LICENSE
Requires-Dist: mistune
